financetoolkit/__init__.py
financetoolkit/discovery/__init__.py
financetoolkit/discovery/discovery_controller.py
financetoolkit/discovery/discovery_model.py
financetoolkit/economics/__init__.py
financetoolkit/economics/ecb_model.py
financetoolkit/economics/economics_controller.py
financetoolkit/economics/fed_model.py
financetoolkit/economics/oecd_model.py
financetoolkit/fundamentals_model.py
financetoolkit/helpers.py
financetoolkit/historical_model.py
financetoolkit/models/__init__.py
financetoolkit/models/altman_model.py
financetoolkit/models/dupont_model.py
financetoolkit/models/enterprise_model.py
financetoolkit/models/growth_model.py
financetoolkit/models/intrinsic_model.py
financetoolkit/models/models_controller.py
financetoolkit/models/piotroski_model.py
financetoolkit/models/wacc_model.py
financetoolkit/normalization/balance.csv
financetoolkit/normalization/cash.csv
financetoolkit/normalization/income.csv
financetoolkit/normalization/statistics.csv
financetoolkit/normalization_model.py
financetoolkit/options/__init__.py
financetoolkit/options/black_scholes_model.py
financetoolkit/options/greeks_model.py
financetoolkit/options/helpers.py
financetoolkit/options/options_controller.py
financetoolkit/options/options_model.py
financetoolkit/performance/__init__.py
financetoolkit/performance/helpers.py
financetoolkit/performance/performance_controller.py
financetoolkit/performance/performance_model.py
financetoolkit/ratios/__init__.py
financetoolkit/ratios/efficiency_model.py
financetoolkit/ratios/liquidity_model.py
financetoolkit/ratios/profitability_model.py
financetoolkit/ratios/ratios_controller.py
financetoolkit/ratios/solvency_model.py
financetoolkit/ratios/valuation_model.py
financetoolkit/risk/__init__.py
financetoolkit/risk/cvar_model.py
financetoolkit/risk/evar_model.py
financetoolkit/risk/garch_model.py
financetoolkit/risk/helpers.py
financetoolkit/risk/risk_controller.py
financetoolkit/risk/risk_model.py
financetoolkit/risk/var_model.py
financetoolkit-1.8.0.dist-info/LICENSE.txt
financetoolkit-1.8.0.dist-info/METADATA
financetoolkit-1.8.0.dist-info/WHEEL
financetoolkit-1.8.0.dist-info/RECORD
