Metadata-Version: 2.1
Name: financetoolkit
Version: 1.8.0
Summary: Transparent and Efficient Financial Analysis
Home-page: https://www.jeroenbouma.com/projects/financetoolkit
License: MIT
Keywords: Finance,Toolkit,Financial,Analysis,Fundamental,Technical,Quantitative,Database,Equities,Currencies,Economics,ETFs,Funds,Indices,Moneymarkets,Commodities,Options
Author: Jeroen Bouma
Requires-Python: >=3.10,<3.13
Classifier: Development Status :: 5 - Production/Stable
Classifier: Intended Audience :: Financial and Insurance Industry
Classifier: License :: OSI Approved :: MIT License
Classifier: Operating System :: OS Independent
Classifier: Programming Language :: Python :: 3
Classifier: Programming Language :: Python :: 3.10
Classifier: Programming Language :: Python :: 3.11
Classifier: Programming Language :: Python :: 3.12
Classifier: Topic :: Office/Business :: Financial :: Investment
Requires-Dist: pandas[computation,performance,plot] (>=2.1.0,<3.0.0)
Requires-Dist: requests (>=2.31.0,<3.0.0)
Requires-Dist: scikit-learn (>=1.3.1,<2.0.0)
Project-URL: Repository, https://github.com/JerBouma/FinanceToolkit
